.gitattributes
.gitignore
CHANGELOG.md
DEVELOPMENT_NOTES.md
LICENSE.txt
MANIFEST.in
README.md
glparchis.desktop
glparchis.epj
glparchis.pro
setup.py
database/dump.sql
doc/Doxyfile
doc/glparchis-players-3.png
doc/glparchis-players-4.png
doc/glparchis-players-6.png
doc/glparchis-players-8.png
doc/index.dox
glparchis/__init__.py
glparchis/functions.py
glparchis/glparchis.py
glparchis/libglparchis.py
glparchis/libglparchistypes.py
glparchis/libmanagers.py
glparchis/loggingsystem.py
glparchis/shortcuts.py
glparchis/version.py
glparchis.egg-info/PKG-INFO
glparchis.egg-info/SOURCES.txt
glparchis.egg-info/dependency_links.txt
glparchis.egg-info/entry_points.txt
glparchis.egg-info/not-zip-safe
glparchis.egg-info/requires.txt
glparchis.egg-info/top_level.txt
glparchis/i18n/glparchis_en.qm
glparchis/i18n/glparchis_en.ts
glparchis/i18n/glparchis_es.qm
glparchis/i18n/glparchis_es.ts
glparchis/i18n/glparchis_fr.qm
glparchis/i18n/glparchis_fr.ts
glparchis/i18n/glparchis_ro.qm
glparchis/i18n/glparchis_ro.ts
glparchis/i18n/glparchis_ru.qm
glparchis/i18n/glparchis_ru.ts
glparchis/images/0.png
glparchis/images/1.png
glparchis/images/2.png
glparchis/images/3.png
glparchis/images/4.png
glparchis/images/5.png
glparchis/images/6.png
glparchis/images/7.png
glparchis/images/8.png
glparchis/images/9.png
glparchis/images/Numeros.xcf
glparchis/images/casillainicial.png
glparchis/images/configure.png
glparchis/images/corona.png
glparchis/images/cube.png
glparchis/images/cube1.png
glparchis/images/cube2.png
glparchis/images/cube3.png
glparchis/images/cube4.png
glparchis/images/cube5.png
glparchis/images/cube6.png
glparchis/images/cube_transparent.png
glparchis/images/dado_desplegado.png
glparchis/images/exit.png
glparchis/images/fichaamarilla.png
glparchis/images/fichaazul.png
glparchis/images/fichacyan.png
glparchis/images/fichagris.png
glparchis/images/fichanaranja.png
glparchis/images/ficharoja.png
glparchis/images/ficharosa.png
glparchis/images/fichaverde.png
glparchis/images/france.png
glparchis/images/fullscreen.png
glparchis/images/game3.png
glparchis/images/game4.png
glparchis/images/game6.png
glparchis/images/game8.png
glparchis/images/glparchis.ico
glparchis/images/glparchis.png
glparchis/images/glparchis.qrc
