Metadata-Version: 2.1
Name: glparchis
Version: 20221204
Summary: Parchís game
Home-page: https://github.com/turulomio/glparchis
Author: turulomio
Author-email: turulomio@yahoo.es
License: GPL-3
Keywords: parchís game
Classifier: Development Status :: 4 - Beta
Classifier: Intended Audience :: Developers
Classifier: Topic :: Software Development :: Build Tools
Classifier: License :: OSI Approved :: GNU General Public License v3 (GPLv3)
Classifier: Programming Language :: Python :: 3
License-File: LICENSE.txt
